notebooklog/__init__.py
notebooklog-0.0.2.dist-info/LICENSE
notebooklog-0.0.2.dist-info/METADATA
notebooklog-0.0.2.dist-info/WHEEL
notebooklog-0.0.2.dist-info/top_level.txt
notebooklog-0.0.2.dist-info/RECORD
