Metadata-Version: 2.1
Name: notebooklog
Version: 0.0.2
Summary: notebooklog
Home-page: https://github.com/maximz/notebooklog
Author: Maxim Zaslavsky
Author-email: maxim@maximz.com
License: MIT license
Classifier: Development Status :: 2 - Pre-Alpha
Classifier: Intended Audience :: Developers
Classifier: License :: OSI Approved :: MIT License
Classifier: Natural Language :: English
Classifier: Programming Language :: Python :: 3
Classifier: Programming Language :: Python :: 3.8
Classifier: Programming Language :: Python :: 3.9
Requires-Python: >=3.8
License-File: LICENSE
Requires-Dist: ipynbname (>=2023.1.0.0)
Requires-Dist: python-slugify
